mingwtomsys/__init__.py
mingwtomsys/__main__.py
mingwtomsys-0.0.2.dist-info/LICENSE
mingwtomsys-0.0.2.dist-info/METADATA
mingwtomsys-0.0.2.dist-info/WHEEL
mingwtomsys-0.0.2.dist-info/entry_points.txt
mingwtomsys-0.0.2.dist-info/top_level.txt
mingwtomsys-0.0.2.dist-info/RECORD
