Metadata-Version: 2.1
Name: mingwtomsys
Version: 0.0.2
Summary: PKGBUILD converter for msys2
Home-page: https://github.com/mugiseyebrows/mingw-to-msys
Author: Stanislav Doronin
Author-email: mugisbrows@gmail.com
License: UNKNOWN
Platform: UNKNOWN
